mopidy_funkwhale/__init__.py
mopidy_funkwhale/actor.py
mopidy_funkwhale/client.py
mopidy_funkwhale/commands.py
mopidy_funkwhale/ext.conf
mopidy_funkwhale/library.py
mopidy_funkwhale-1.1.0.dist-info/LICENSE
mopidy_funkwhale-1.1.0.dist-info/METADATA
mopidy_funkwhale-1.1.0.dist-info/WHEEL
mopidy_funkwhale-1.1.0.dist-info/entry_points.txt
mopidy_funkwhale-1.1.0.dist-info/top_level.txt
mopidy_funkwhale-1.1.0.dist-info/zip-safe
mopidy_funkwhale-1.1.0.dist-info/RECORD
