Metadata-Version: 2.1
Name: mopidy-funkwhale
Version: 1.1.0
Summary: "A backend extension for mopidy to stream music from a Funkwhale server"
Home-page: https://dev.funkwhale.audio/funkwhale/mopidy
Author: The Funkwhale Collective
Author-email: maintainers@funkwhale.audio
License: GLP-3
Keywords: code,diff,copy-paste,linter,DRY
Platform: UNKNOWN
Classifier: Programming Language :: Python :: 3
Classifier: Programming Language :: Python :: 3.6
License-File: LICENSE
Requires-Dist: mopidy (>=3)
Requires-Dist: requests
Requires-Dist: requests-oauthlib
Requires-Dist: pygobject
Requires-Dist: vext
Provides-Extra: build
Requires-Dist: setuptools ; extra == 'build'
Requires-Dist: wheel ; extra == 'build'
Provides-Extra: dev
Requires-Dist: ipython ; extra == 'dev'
Requires-Dist: ipdb ; extra == 'dev'
Provides-Extra: lint
Requires-Dist: black ; extra == 'lint'
Provides-Extra: publish
Requires-Dist: twine ; extra == 'publish'
Provides-Extra: test
Requires-Dist: pytest ; extra == 'test'
Requires-Dist: pytest-cov ; extra == 'test'
Requires-Dist: requests-mock ; extra == 'test'
Requires-Dist: pytest-mock ; extra == 'test'
Requires-Dist: factory-boy ; extra == 'test'
